{"assets/fonts/Inconsolata-Bold.ttf":["assets/fonts/Inconsolata-Bold.ttf"],"assets/fonts/Inconsolata-Medium.ttf":["assets/fonts/Inconsolata-Medium.ttf"],"assets/fonts/Inconsolata-Regular.ttf":["assets/fonts/Inconsolata-Regular.ttf"],"assets/fonts/Inconsolata-SemiBold.ttf":["assets/fonts/Inconsolata-SemiBold.ttf"],"assets/icons/music.png":["assets/icons/music.png"],"assets/icons/phone.png":["assets/icons/phone.png"],"assets/icons/rocket.png":["assets/icons/rocket.png"],"assets/icons/wave.png":["assets/icons/wave.png"]}